{
  "products": [
    {
      "id": 1,
      "name": "Admin Dashboard Pro",
      "price": 15,
      "image": "/products/1.webp",
      "category": "Dashboard",
      "userId": 1,
      "createdAt": "2024-12-12T10:58:33.000Z"
    },
    {
      "id": 2,
      "name": "Admin Pro",
      "price": 215,
      "image": "/products/1.webp",
      "category": "Dashboard",
      "userId": 1,
      "createdAt": "2024-12-12T10:58:33.000Z"
    },
    {
      "id": 3,
      "name": "Admin Pro",
      "price": 215,
      "image": "/products/nextjs-1734000964174.webp",
      "category": "Dashboard",
      "userId": 1,
      "createdAt": "2024-12-12T10:58:33.000Z"
    },
    {
      "name": "React JS",
      "price": 120,
      "image": "/products/react-js-1734001514910.webp",
      "category": "Dashboard",
      "userId": 1,
      "id": 4,
      "createdAt": "2024-12-12T11:05:14.968Z"
    },
    {
      "name": "The NextJS",
      "price": 55,
      "image": "/products/the-nextjs-1734008484571.webp",
      "category": "Landing Page",
      "userId": 1,
      "id": 5,
      "createdAt": "2024-12-12T13:01:25.625Z"
    }
  ]
}